django_enummodel-0.2.1.dist-info/DESCRIPTION.rst
django_enummodel-0.2.1.dist-info/METADATA
django_enummodel-0.2.1.dist-info/RECORD
django_enummodel-0.2.1.dist-info/WHEEL
django_enummodel-0.2.1.dist-info/metadata.json
django_enummodel-0.2.1.dist-info/top_level.txt
enummodel/__init__.py
enummodel/admin.py
enummodel/apps.py
enummodel/models.py
enummodel/settings.py
enummodel/widgets.py
enummodel/tests/__init__.py
enummodel/tests/admin.py
enummodel/tests/models.py
enummodel/tests/test_urls.py
