Metadata-Version: 2.0
Name: django-enummodel
Version: 0.2.1
Summary: A Django application to bridge the gap between using enumerations and having fully-specified, normalized data models.
Home-page: http://github.com/yorkedork/django-enummodel/tree/master
Author: Thom Linton
Author-email: thom.linton@gmail.com
License: BSD
Platform: UNKNOWN
Classifier: Development Status :: 4 - Beta
Classifier: Environment :: Web Environment
Classifier: Framework :: Django
Classifier: Intended Audience :: Developers
Classifier: Programming Language :: Python
Classifier: Topic :: Software Development :: Libraries :: Python Modules
Classifier: License :: OSI Approved :: BSD License
Requires-Dist: Django (>=1.8)
Requires-Dist: six (>=1.10.0)
